{"league_name":"Proliga","season_key":"2025_2026","metrics":[{"key":"net_rating_avg","label":"Net Rating","format":"signed1","higher_is_better":true},{"key":"off_rating_avg","label":"ORtg","format":"num1","higher_is_better":true},{"key":"def_rating_avg","label":"DRtg","format":"num1","higher_is_better":false},{"key":"pace_avg","label":"Pace","format":"num1","higher_is_better":true},{"key":"efg_pct_off_avg","label":"eFG%","format":"pct1","higher_is_better":true},{"key":"tov_pct_off_avg","label":"TOV%","format":"pct1","higher_is_better":false},{"key":"orb_pct_off_avg","label":"REB%","format":"pct1","higher_is_better":true}],"teams":[{"team_key":"AAC","team_name":"AAC"},{"team_key":"ADG","team_name":"ADG"},{"team_key":"BSA","team_name":"BSA"},{"team_key":"CAB","team_name":"CAB"},{"team_key":"CBQ","team_name":"CBQ"},{"team_key":"CDP","team_name":"CDP"},{"team_key":"GAL","team_name":"GAL"},{"team_key":"GCO","team_name":"GCO"},{"team_key":"GIN","team_name":"GIN"},{"team_key":"IBC","team_name":"IBC"},{"team_key":"ILL","team_name":"ILL"},{"team_key":"MBC","team_name":"MBC"},{"team_key":"PSC","team_name":"PSC"},{"team_key":"SBC","team_name":"SBC"},{"team_key":"SCL","team_name":"SCL"},{"team_key":"SDC","team_name":"SDC"},{"team_key":"SLB","team_name":"SLB"}],"summary":[{"team_key":"AAC","opp_team_key":"ADG","team_name":"Académica Efapel","opponent_name":"AD Galomar","games":2,"wins":1,"losses":1,"win_pct":0.5,"net_rating_avg":0.5138271658666156,"off_rating_avg":101.25064562286703,"def_rating_avg":100.73681845700041,"pace_avg":79.28,"efg_pct_off_avg":0.452054794520548,"tov_pct_off_avg":0.1319693689647884,"orb_pct_off_avg":0.277389903329753},{"team_key":"AAC","opp_team_key":"BSA","team_name":"Académica Efapel","opponent_name":"BSA - GALP","games":2,"wins":1,"losses":1,"win_pct":0.5,"net_rating_avg":-1.443414319167637,"off_rating_avg":90.05104900481439,"def_rating_avg":91.49446332398202,"pace_avg":73.22,"efg_pct_off_avg":0.4353056900726392,"tov_pct_off_avg":0.17024282611234653,"orb_pct_off_avg":0.16856060606060608},{"team_key":"AAC","opp_team_key":"CBQ","team_name":"Académica Efapel","opponent_name":"Clube Basket de Queluz","games":2,"wins":0,"losses":2,"win_pct":0.0,"net_rating_avg":-13.152186021062178,"off_rating_avg":80.07051758510221,"def_rating_avg":93.2227036061644,"pace_avg":67.49000000000001,"efg_pct_off_avg":0.40716322166785457,"tov_pct_off_avg":0.2302390870958077,"orb_pct_off_avg":0.27142857142857146},{"team_key":"AAC","opp_team_key":"CDP","team_name":"Académica Efapel","opponent_name":"CD Póvoa / Esc Online","games":2,"wins":0,"losses":2,"win_pct":0.0,"net_rating_avg":-55.380387560694665,"off_rating_avg":67.051784728207,"def_rating_avg":122.43217228890165,"pace_avg":83.36999999999999,"efg_pct_off_avg":0.36171726755218214,"tov_pct_off_avg":0.2618752758132303,"orb_pct_off_avg":0.2173913043478261},{"team_key":"AAC","opp_team_key":"GIN","team_name":"Académica Efapel","opponent_name":"Casino Ginásio","games":2,"wins":0,"losses":2,"win_pct":0.0,"net_rating_avg":-23.082404545142154,"off_rating_avg":92.06723081843005,"def_rating_avg":115.1496353635722,"pace_avg":76.23,"efg_pct_off_avg":0.44666666666666666,"tov_pct_off_avg":0.17752740809984174,"orb_pct_off_avg":0.22657952069716775},{"team_key":"AAC","opp_team_key":"ILL","team_name":"Académica Efapel","opponent_name":"Illiabum Clube","games":2,"wins":0,"losses":2,"win_pct":0.0,"net_rating_avg":-39.85743457735377,"off_rating_avg":66.8281012337333,"def_rating_avg":106.68553581108708,"pace_avg":77.75999999999999,"efg_pct_off_avg":0.38039617486338795,"tov_pct_off_avg":0.2760319841135711,"orb_pct_off_avg":0.21978021978021978},{"team_key":"AAC","opp_team_key":"MBC","team_name":"Académica Efapel","opponent_name":"Maia Basket Clube","games":2,"wins":0,"losses":2,"win_pct":0.0,"net_rating_avg":-35.08763479438996,"off_rating_avg":69.11169720653419,"def_rating_avg":104.19933200092416,"pace_avg":85.31,"efg_pct_off_avg":0.3685515873015873,"tov_pct_off_avg":0.2822010625664535,"orb_pct_off_avg":0.22916666666666669},{"team_key":"AAC","opp_team_key":"SBC","team_name":"Académica Efapel","opponent_name":"Sampaense Inspecentro","games":3,"wins":1,"losses":2,"win_pct":0.3333333333333333,"net_rating_avg":-14.749009695268251,"off_rating_avg":84.90821751555181,"def_rating_avg":99.65722721082007,"pace_avg":72.59333333333332,"efg_pct_off_avg":0.43679378531073443,"tov_pct_off_avg":0.2460504084513202,"orb_pct_off_avg":0.25958855647669776},{"team_key":"AAC","opp_team_key":"SCL","team_name":"Académica Efapel","opponent_name":"Sport Club Lusitânia","games":3,"wins":0,"losses":3,"win_pct":0.0,"net_rating_avg":-21.81255446502959,"off_rating_avg":89.16729389383543,"def_rating_avg":110.97984835886501,"pace_avg":77.72666666666667,"efg_pct_off_avg":0.482078853046595,"tov_pct_off_avg":0.21762792870132738,"orb_pct_off_avg":0.19396597554492293},{"team_key":"AAC","opp_team_key":"SDC","team_name":"Académica Efapel","opponent_name":"Sangalhos","games":4,"wins":0,"losses":4,"win_pct":0.0,"net_rating_avg":-8.018572092694349,"off_rating_avg":84.9485635161281,"def_rating_avg":92.96713560882245,"pace_avg":75.625,"efg_pct_off_avg":0.4180189047632695,"tov_pct_off_avg":0.21365592143687065,"orb_pct_off_avg":0.2797053386092372},{"team_key":"AAC","opp_team_key":"SLB","team_name":"Académica Efapel","opponent_name":"SL Benfica","games":1,"wins":0,"losses":1,"win_pct":0.0,"net_rating_avg":-6.771955765993937,"off_rating_avg":76.00950118764845,"def_rating_avg":82.78145695364239,"pace_avg":84.38,"efg_pct_off_avg":0.35344827586206895,"tov_pct_off_avg":0.26128266033254155,"orb_pct_off_avg":0.21951219512195122},{"team_key":"ADG","opp_team_key":"AAC","team_name":"AD Galomar","opponent_name":"Académica Efapel","games":2,"wins":1,"losses":1,"win_pct":0.5,"net_rating_avg":-0.5138271658666156,"off_rating_avg":100.73681845700041,"def_rating_avg":101.25064562286703,"pace_avg":79.28,"efg_pct_off_avg":0.5034021071115014,"tov_pct_off_avg":0.20115635156649403,"orb_pct_off_avg":0.2710365853658537},{"team_key":"ADG","opp_team_key":"BSA","team_name":"AD Galomar","opponent_name":"BSA - GALP","games":3,"wins":3,"losses":0,"win_pct":1.0,"net_rating_avg":9.105852545811453,"off_rating_avg":108.41523896563429,"def_rating_avg":99.30938641982283,"pace_avg":76.9,"efg_pct_off_avg":0.5356919023317089,"tov_pct_off_avg":0.17959966486262777,"orb_pct_off_avg":0.26944444444444443},{"team_key":"ADG","opp_team_key":"CAB","team_name":"AD Galomar","opponent_name":"CAB Madeira","games":2,"wins":0,"losses":2,"win_pct":0.0,"net_rating_avg":-11.115174378705731,"off_rating_avg":112.13168878258287,"def_rating_avg":123.24686316128859,"pace_avg":77.34,"efg_pct_off_avg":0.5476863061608824,"tov_pct_off_avg":0.2066867455670784,"orb_pct_off_avg":0.3173076923076923},{"team_key":"ADG","opp_team_key":"CBQ","team_name":"AD Galomar","opponent_name":"Clube Basket de Queluz","games":4,"wins":4,"losses":0,"win_pct":1.0,"net_rating_avg":25.043076867368338,"off_rating_avg":112.6485208839401,"def_rating_avg":87.60544401657175,"pace_avg":76.65,"efg_pct_off_avg":0.5351865327614986,"tov_pct_off_avg":0.17379380037620545,"orb_pct_off_avg":0.3599510484321531},{"team_key":"ADG","opp_team_key":"GCO","team_name":"AD Galomar","opponent_name":"Ginásio ANTRIX","games":1,"wins":1,"losses":0,"win_pct":1.0,"net_rating_avg":3.1834318838401146,"off_rating_avg":94.98123827392119,"def_rating_avg":91.79780639008108,"pace_avg":84.58,"efg_pct_off_avg":0.5071428571428571,"tov_pct_off_avg":0.29315196998123827,"orb_pct_off_avg":0.375},{"team_key":"ADG","opp_team_key":"IBC","team_name":"AD Galomar","opponent_name":"Imortal LUZiGÁS","games":2,"wins":0,"losses":2,"win_pct":0.0,"net_rating_avg":-5.929289264644339,"off_rating_avg":102.05265225759743,"def_rating_avg":107.98194152224177,"pace_avg":80.31888888888889,"efg_pct_off_avg":0.493421052631579,"tov_pct_off_avg":0.1883768386572725,"orb_pct_off_avg":0.24871794871794872},{"team_key":"ADG","opp_team_key":"PSC","team_name":"AD Galomar","opponent_name":"Portimonense SC","games":2,"wins":1,"losses":1,"win_pct":0.5,"net_rating_avg":1.3915980137677764,"off_rating_avg":113.32808876623744,"def_rating_avg":111.93649075246967,"pace_avg":74.83,"efg_pct_off_avg":0.49682539682539684,"tov_pct_off_avg":0.15589723633604194,"orb_pct_off_avg":0.3751342642320086},{"team_key":"ADG","opp_team_key":"SCL","team_name":"AD Galomar","opponent_name":"Sport Club Lusitânia","games":2,"wins":0,"losses":2,"win_pct":0.0,"net_rating_avg":-12.29615096834393,"off_rating_avg":109.95371686548324,"def_rating_avg":122.24986783382717,"pace_avg":77.03,"efg_pct_off_avg":0.5307765151515151,"tov_pct_off_avg":0.20001179821917964,"orb_pct_off_avg":0.4027777777777778},{"team_key":"ADG","opp_team_key":"SDC","team_name":"AD Galomar","opponent_name":"Sangalhos","games":2,"wins":2,"losses":0,"win_pct":1.0,"net_rating_avg":38.63002532145876,"off_rating_avg":128.25133319798883,"def_rating_avg":89.62130787653007,"pace_avg":79.07,"efg_pct_off_avg":0.6297101449275362,"tov_pct_off_avg":0.1574422571617755,"orb_pct_off_avg":0.33192567567567566},{"team_key":"ADG","opp_team_key":"SLB","team_name":"AD Galomar","opponent_name":"SL Benfica","games":4,"wins":3,"losses":1,"win_pct":0.75,"net_rating_avg":0.5059713442895131,"off_rating_avg":96.48224831350862,"def_rating_avg":95.97627696921911,"pace_avg":78.66499999999999,"efg_pct_off_avg":0.4593269240842184,"tov_pct_off_avg":0.24021819006242198,"orb_pct_off_avg":0.36399262899262896},{"team_key":"BSA","opp_team_key":"AAC","team_name":"BSA - GALP","opponent_name":"Académica Efapel","games":2,"wins":1,"losses":1,"win_pct":0.5,"net_rating_avg":1.443414319167637,"off_rating_avg":91.49446332398202,"def_rating_avg":90.05104900481439,"pace_avg":73.22,"efg_pct_off_avg":0.40184944841012327,"tov_pct_off_avg":0.1993560217184832,"orb_pct_off_avg":0.36920133907221425},{"team_key":"BSA","opp_team_key":"ADG","team_name":"BSA - GALP","opponent_name":"AD Galomar","games":3,"wins":0,"losses":3,"win_pct":0.0,"net_rating_avg":-9.105852545811453,"off_rating_avg":99.30938641982283,"def_rating_avg":108.41523896563429,"pace_avg":76.9,"efg_pct_off_avg":0.49603174603174605,"tov_pct_off_avg":0.20936593516292198,"orb_pct_off_avg":0.24799498746867166},{"team_key":"BSA","opp_team_key":"CAB","team_name":"BSA - GALP","opponent_name":"CAB Madeira","games":2,"wins":0,"losses":2,"win_pct":0.0,"net_rating_avg":-23.921612069348384,"off_rating_avg":87.46498357696197,"def_rating_avg":111.38659564631035,"pace_avg":79.93,"efg_pct_off_avg":0.4823863636363636,"tov_pct_off_avg":0.3041170747174713,"orb_pct_off_avg":0.23794642857142856},{"team_key":"BSA","opp_team_key":"CBQ","team_name":"BSA - GALP","opponent_name":"Clube Basket de Queluz","games":4,"wins":3,"losses":1,"win_pct":0.75,"net_rating_avg":7.711124948167953,"off_rating_avg":99.18256392587415,"def_rating_avg":91.47143897770619,"pace_avg":76.13555555555556,"efg_pct_off_avg":0.45864239926739925,"tov_pct_off_avg":0.2331035084865818,"orb_pct_off_avg":0.39210255423647666},{"team_key":"BSA","opp_team_key":"GCO","team_name":"BSA - GALP","opponent_name":"Ginásio ANTRIX","games":2,"wins":0,"losses":2,"win_pct":0.0,"net_rating_avg":-11.214958574019661,"off_rating_avg":85.97895061413047,"def_rating_avg":97.19390918815014,"pace_avg":82.52,"efg_pct_off_avg":0.3842021985343105,"tov_pct_off_avg":0.17914419477022106,"orb_pct_off_avg":0.3123076923076923},{"team_key":"BSA","opp_team_key":"IBC","team_name":"BSA - GALP","opponent_name":"Imortal LUZiGÁS","games":2,"wins":0,"losses":2,"win_pct":0.0,"net_rating_avg":-14.129320920341229,"off_rating_avg":97.36047437340434,"def_rating_avg":111.48979529374557,"pace_avg":77.82,"efg_pct_off_avg":0.45636721113127643,"tov_pct_off_avg":0.2047004968841793,"orb_pct_off_avg":0.27266081871345027},{"team_key":"BSA","opp_team_key":"PSC","team_name":"BSA - GALP","opponent_name":"Portimonense SC","games":2,"wins":0,"losses":2,"win_pct":0.0,"net_rating_avg":-25.547721434117392,"off_rating_avg":85.15894093197323,"def_rating_avg":110.70666236609063,"pace_avg":78.78999999999999,"efg_pct_off_avg":0.4073317307692308,"tov_pct_off_avg":0.20977625935616345,"orb_pct_off_avg":0.24151643690349947},{"team_key":"BSA","opp_team_key":"SBC","team_name":"BSA - GALP","opponent_name":"Sampaense Inspecentro","games":1,"wins":1,"losses":0,"win_pct":1.0,"net_rating_avg":32.2933226034129,"off_rating_avg":98.73417721518987,"def_rating_avg":66.44085461177697,"pace_avg":77.88,"efg_pct_off_avg":0.4552238805970149,"tov_pct_off_avg":0.26582278481012656,"orb_pct_off_avg":0.45454545454545453},{"team_key":"BSA","opp_team_key":"SCL","team_name":"BSA - GALP","opponent_name":"Sport Club Lusitânia","games":2,"wins":0,"losses":2,"win_pct":0.0,"net_rating_avg":-8.178734621032852,"off_rating_avg":90.37208146511892,"def_rating_avg":98.55081608615177,"pace_avg":80.42,"efg_pct_off_avg":0.5118534482758621,"tov_pct_off_avg":0.22157698982374874,"orb_pct_off_avg":0.13333333333333333},{"team_key":"BSA","opp_team_key":"SDC","team_name":"BSA - GALP","opponent_name":"Sangalhos","games":1,"wins":1,"losses":0,"win_pct":1.0,"net_rating_avg":17.104560472580232,"off_rating_avg":124.70657276995306,"def_rating_avg":107.60201229737282,"pace_avg":69.86,"efg_pct_off_avg":0.6083333333333333,"tov_pct_off_avg":0.20539906103286387,"orb_pct_off_avg":0.375},{"team_key":"BSA","opp_team_key":"SLB","team_name":"BSA - GALP","opponent_name":"SL Benfica","games":4,"wins":2,"losses":2,"win_pct":0.5,"net_rating_avg":0.187475034935499,"off_rating_avg":86.38723470505052,"def_rating_avg":86.19975967011501,"pace_avg":78.32,"efg_pct_off_avg":0.40836158915671017,"tov_pct_off_avg":0.23303592235794768,"orb_pct_off_avg":0.26563020313020314},{"team_key":"CAB","opp_team_key":"ADG","team_name":"CAB Madeira","opponent_name":"AD Galomar","games":2,"wins":2,"losses":0,"win_pct":1.0,"net_rating_avg":11.115174378705731,"off_rating_avg":123.24686316128859,"def_rating_avg":112.13168878258287,"pace_avg":77.34,"efg_pct_off_avg":0.6387030365414308,"tov_pct_off_avg":0.20157715145490207,"orb_pct_off_avg":0.2976539589442815},{"team_key":"CAB","opp_team_key":"BSA","team_name":"CAB Madeira","opponent_name":"BSA - GALP","games":2,"wins":2,"losses":0,"win_pct":1.0,"net_rating_avg":23.921612069348384,"off_rating_avg":111.38659564631035,"def_rating_avg":87.46498357696197,"pace_avg":79.93,"efg_pct_off_avg":0.5381455399061033,"tov_pct_off_avg":0.1845672529391172,"orb_pct_off_avg":0.33802376485303315},{"team_key":"CAB","opp_team_key":"CBQ","team_name":"CAB Madeira","opponent_name":"Clube Basket de Queluz","games":2,"wins":2,"losses":0,"win_pct":1.0,"net_rating_avg":46.91172971670077,"off_rating_avg":133.57748704160542,"def_rating_avg":86.66575732490466,"pace_avg":77.52000000000001,"efg_pct_off_avg":0.6528272748871466,"tov_pct_off_avg":0.16170274690245862,"orb_pct_off_avg":0.3666666666666667},{"team_key":"CAB","opp_team_key":"CDP","team_name":"CAB Madeira","opponent_name":"CD Póvoa / Esc Online","games":2,"wins":1,"losses":1,"win_pct":0.5,"net_rating_avg":-0.3571960734457278,"off_rating_avg":102.54841885177467,"def_rating_avg":102.90561492522039,"pace_avg":73.25,"efg_pct_off_avg":0.5592436974789916,"tov_pct_off_avg":0.22025015609338333,"orb_pct_off_avg":0.2690166975881262},{"team_key":"CAB","opp_team_key":"GCO","team_name":"CAB Madeira","opponent_name":"Ginásio ANTRIX","games":2,"wins":2,"losses":0,"win_pct":1.0,"net_rating_avg":15.110552856674992,"off_rating_avg":112.39574019629315,"def_rating_avg":97.28518733961815,"pace_avg":74.92000000000002,"efg_pct_off_avg":0.49642857142857144,"tov_pct_off_avg":0.16676629914307478,"orb_pct_off_avg":0.4074675324675324},{"team_key":"CAB","opp_team_key":"GIN","team_name":"CAB Madeira","opponent_name":"Casino Ginásio","games":2,"wins":2,"losses":0,"win_pct":1.0,"net_rating_avg":20.661216400732727,"off_rating_avg":124.0339355112361,"def_rating_avg":103.37271911050337,"pace_avg":76.52000000000001,"efg_pct_off_avg":0.6153508771929824,"tov_pct_off_avg":0.16847255770909825,"orb_pct_off_avg":0.3239775461106656},{"team_key":"CAB","opp_team_key":"IBC","team_name":"CAB Madeira","opponent_name":"Imortal LUZiGÁS","games":3,"wins":3,"losses":0,"win_pct":1.0,"net_rating_avg":14.264110949259873,"off_rating_avg":108.47433354201945,"def_rating_avg":94.21022259275958,"pace_avg":77.80666666666666,"efg_pct_off_avg":0.5358375930409829,"tov_pct_off_avg":0.21024765234292797,"orb_pct_off_avg":0.2680316091954023},{"team_key":"CAB","opp_team_key":"ILL","team_name":"CAB Madeira","opponent_name":"Illiabum MARGRES","games":2,"wins":2,"losses":0,"win_pct":1.0,"net_rating_avg":5.062054382020754,"off_rating_avg":93.4114137892361,"def_rating_avg":88.34935940721533,"pace_avg":72.64,"efg_pct_off_avg":0.48660714285714285,"tov_pct_off_avg":0.16601238713409938,"orb_pct_off_avg":0.14007936507936508},{"team_key":"CAB","opp_team_key":"MBC","team_name":"CAB Madeira","opponent_name":"Maia Basket Clube","games":2,"wins":0,"losses":2,"win_pct":0.0,"net_rating_avg":-8.975651529847624,"off_rating_avg":100.25551659254191,"def_rating_avg":109.23116812238953,"pace_avg":81.24111111111111,"efg_pct_off_avg":0.4409377387318564,"tov_pct_off_avg":0.18680240762914813,"orb_pct_off_avg":0.33043478260869563},{"team_key":"CAB","opp_team_key":"PSC","team_name":"CAB Madeira","opponent_name":"Portimonense SC","games":4,"wins":2,"losses":2,"win_pct":0.5,"net_rating_avg":0.42239413512751867,"off_rating_avg":103.33353729810017,"def_rating_avg":102.91114316297265,"pace_avg":72.18777777777778,"efg_pct_off_avg":0.4547680966428205,"tov_pct_off_avg":0.13705481391102678,"orb_pct_off_avg":0.30435897435897435},{"team_key":"CAB","opp_team_key":"SLB","team_name":"CAB Madeira","opponent_name":"SL Benfica","games":2,"wins":2,"losses":0,"win_pct":1.0,"net_rating_avg":14.243218108024799,"off_rating_avg":96.79664737653066,"def_rating_avg":82.55342926850585,"pace_avg":77.24000000000001,"efg_pct_off_avg":0.44134424603174605,"tov_pct_off_avg":0.1886623282836333,"orb_pct_off_avg":0.2902467685076381},{"team_key":"CBQ","opp_team_key":"AAC","team_name":"Clube Basket de Queluz","opponent_name":"Académica Efapel","games":2,"wins":2,"losses":0,"win_pct":1.0,"net_rating_avg":13.152186021062178,"off_rating_avg":93.2227036061644,"def_rating_avg":80.07051758510221,"pace_avg":67.49000000000001,"efg_pct_off_avg":0.3824013157894737,"tov_pct_off_avg":0.11076832359263922,"orb_pct_off_avg":0.29166666666666663},{"team_key":"CBQ","opp_team_key":"ADG","team_name":"Clube Basket de Queluz","opponent_name":"AD Galomar","games":4,"wins":0,"losses":4,"win_pct":0.0,"net_rating_avg":-25.043076867368338,"off_rating_avg":87.60544401657175,"def_rating_avg":112.6485208839401,"pace_avg":76.65,"efg_pct_off_avg":0.44083856660943943,"tov_pct_off_avg":0.21754792896107963,"orb_pct_off_avg":0.28586368977673327},{"team_key":"CBQ","opp_team_key":"BSA","team_name":"Clube Basket de Queluz","opponent_name":"BSA - GALP","games":4,"wins":1,"losses":3,"win_pct":0.25,"net_rating_avg":-7.711124948167953,"off_rating_avg":91.47143897770619,"def_rating_avg":99.18256392587415,"pace_avg":76.13555555555556,"efg_pct_off_avg":0.4388505620442309,"tov_pct_off_avg":0.18598665690395355,"orb_pct_off_avg":0.2554249728451856},{"team_key":"CBQ","opp_team_key":"CAB","team_name":"Clube Basket de Queluz","opponent_name":"CAB Madeira","games":2,"wins":0,"losses":2,"win_pct":0.0,"net_rating_avg":-46.91172971670077,"off_rating_avg":86.66575732490466,"def_rating_avg":133.57748704160542,"pace_avg":77.52000000000001,"efg_pct_off_avg":0.45735294117647063,"tov_pct_off_avg":0.24258259331727872,"orb_pct_off_avg":0.3020334928229665},{"team_key":"CBQ","opp_team_key":"GCO","team_name":"Clube Basket de Queluz","opponent_name":"Ginásio ANTRIX","games":2,"wins":0,"losses":2,"win_pct":0.0,"net_rating_avg":-33.440125151355616,"off_rating_avg":81.25795609786388,"def_rating_avg":114.69808124921951,"pace_avg":79.22999999999999,"efg_pct_off_avg":0.3452943313953488,"tov_pct_off_avg":0.13461329483358173,"orb_pct_off_avg":0.2397598870056497},{"team_key":"CBQ","opp_team_key":"IBC","team_name":"Clube Basket de Queluz","opponent_name":"Imortal LUZiGÁS","games":2,"wins":0,"losses":2,"win_pct":0.0,"net_rating_avg":-7.337023601153106,"off_rating_avg":99.49914961031443,"def_rating_avg":106.83617321146754,"pace_avg":75.95,"efg_pct_off_avg":0.45913256606990627,"tov_pct_off_avg":0.19588918589379006,"orb_pct_off_avg":0.3388888888888889},{"team_key":"CBQ","opp_team_key":"PSC","team_name":"Clube Basket de Queluz","opponent_name":"Portimonense SC","games":2,"wins":0,"losses":2,"win_pct":0.0,"net_rating_avg":-27.634397230543968,"off_rating_avg":82.51646846116893,"def_rating_avg":110.1508656917129,"pace_avg":76.10999999999999,"efg_pct_off_avg":0.40883916703588835,"tov_pct_off_avg":0.1454617122819888,"orb_pct_off_avg":0.15136054421768708},{"team_key":"CBQ","opp_team_key":"SBC","team_name":"Clube Basket de Queluz","opponent_name":"Sampaense Inspecentro","games":2,"wins":1,"losses":1,"win_pct":0.5,"net_rating_avg":6.345343787564005,"off_rating_avg":108.52262271369614,"def_rating_avg":102.17727892613213,"pace_avg":68.99000000000001,"efg_pct_off_avg":0.5346153846153846,"tov_pct_off_avg":0.16327697011735062,"orb_pct_off_avg":0.1882051282051282},{"team_key":"CBQ","opp_team_key":"SCL","team_name":"Clube Basket de Queluz","opponent_name":"Sport Club Lusitânia","games":1,"wins":0,"losses":1,"win_pct":0.0,"net_rating_avg":-6.599548898524063,"off_rating_avg":100.63559322033899,"def_rating_avg":107.23514211886305,"pace_avg":76.46000000000001,"efg_pct_off_avg":0.49295774647887325,"tov_pct_off_avg":0.1853813559322034,"orb_pct_off_avg":0.34210526315789475},{"team_key":"CBQ","opp_team_key":"SDC","team_name":"Clube Basket de Queluz","opponent_name":"Sangalhos","games":2,"wins":2,"losses":0,"win_pct":1.0,"net_rating_avg":26.417854771575684,"off_rating_avg":109.08145833532717,"def_rating_avg":82.66360356375148,"pace_avg":73.89,"efg_pct_off_avg":0.5363145880888152,"tov_pct_off_avg":0.17164261907952033,"orb_pct_off_avg":0.3295454545454546},{"team_key":"CBQ","opp_team_key":"SLB","team_name":"Clube Basket de Queluz","opponent_name":"SL Benfica","games":3,"wins":2,"losses":1,"win_pct":0.6666666666666666,"net_rating_avg":-7.835816386757244,"off_rating_avg":86.83026267943234,"def_rating_avg":94.66607906618958,"pace_avg":76.96,"efg_pct_off_avg":0.4162469899046031,"tov_pct_off_avg":0.2371460855248492,"orb_pct_off_avg":0.2732334238887065},{"team_key":"CDP","opp_team_key":"AAC","team_name":"CD Póvoa / Esc Online","opponent_name":"Académica Efapel","games":2,"wins":2,"losses":0,"win_pct":1.0,"net_rating_avg":55.380387560694665,"off_rating_avg":122.43217228890165,"def_rating_avg":67.051784728207,"pace_avg":83.36999999999999,"efg_pct_off_avg":0.5621323529411765,"tov_pct_off_avg":0.14444897291512443,"orb_pct_off_avg":0.42340425531914894},{"team_key":"CDP","opp_team_key":"CAB","team_name":"CD Póvoa / Esc Online","opponent_name":"CAB Madeira","games":2,"wins":1,"losses":1,"win_pct":0.5,"net_rating_avg":0.3571960734457278,"off_rating_avg":102.90561492522039,"def_rating_avg":102.54841885177467,"pace_avg":73.25,"efg_pct_off_avg":0.41578947368421054,"tov_pct_off_avg":0.13643380021251708,"orb_pct_off_avg":0.4036734693877551},{"team_key":"CDP","opp_team_key":"GCO","team_name":"CD Póvoa / Esc Online","opponent_name":"Ginásio ANTRIX","games":2,"wins":2,"losses":0,"win_pct":1.0,"net_rating_avg":26.32694384832609,"off_rating_avg":103.62594338731911,"def_rating_avg":77.29899953899303,"pace_avg":80.93,"efg_pct_off_avg":0.44550513698630134,"tov_pct_off_avg":0.131551781656585,"orb_pct_off_avg":0.3627450980392157},{"team_key":"CDP","opp_team_key":"GIN","team_name":"CD Póvoa / Esc Online","opponent_name":"Casino Ginásio","games":4,"wins":4,"losses":0,"win_pct":1.0,"net_rating_avg":16.494503412880903,"off_rating_avg":111.31605421427064,"def_rating_avg":94.82155080138973,"pace_avg":79.005,"efg_pct_off_avg":0.5463206543614514,"tov_pct_off_avg":0.19282586011551872,"orb_pct_off_avg":0.30980861244019137},{"team_key":"CDP","opp_team_key":"IBC","team_name":"CD Póvoa / Esc Online","opponent_name":"Imortal LUZiGÁS","games":2,"wins":2,"losses":0,"win_pct":1.0,"net_rating_avg":33.67300681089325,"off_rating_avg":113.09335556218629,"def_rating_avg":79.42034875129303,"pace_avg":79.87,"efg_pct_off_avg":0.5275106837606838,"tov_pct_off_avg":0.18323858991547176,"orb_pct_off_avg":0.41261398176291797},{"team_key":"CDP","opp_team_key":"ILL","team_name":"CD Póvoa / Esc Online","opponent_name":"Illiabum MARGRES","games":4,"wins":4,"losses":0,"win_pct":1.0,"net_rating_avg":19.21268079467704,"off_rating_avg":98.25461624599038,"def_rating_avg":79.04193545131334,"pace_avg":76.635,"efg_pct_off_avg":0.5172564554714327,"tov_pct_off_avg":0.21143845163437944,"orb_pct_off_avg":0.2787001287001287},{"team_key":"CDP","opp_team_key":"MBC","team_name":"CD Póvoa / Esc Online","opponent_name":"Maia Basket Clube","games":3,"wins":3,"losses":0,"win_pct":1.0,"net_rating_avg":20.62182916209066,"off_rating_avg":108.42406699735766,"def_rating_avg":87.80223783526701,"pace_avg":84.13333333333333,"efg_pct_off_avg":0.5380004430637342,"tov_pct_off_avg":0.20313315170652335,"orb_pct_off_avg":0.37817460317460316},{"team_key":"CDP","opp_team_key":"PSC","team_name":"CD Póvoa / Esc Online","opponent_name":"Portimonense SC","games":1,"wins":0,"losses":1,"win_pct":0.0,"net_rating_avg":-5.751161897094335,"off_rating_avg":89.20076117982873,"def_rating_avg":94.95192307692307,"pace_avg":74.34666666666666,"efg_pct_off_avg":0.4235294117647059,"tov_pct_off_avg":0.1665080875356803,"orb_pct_off_avg":0.33962264150943394},{"team_key":"CDP","opp_team_key":"SBC","team_name":"CD Póvoa / Esc Online","opponent_name":"Sampaense Inspecentro","games":2,"wins":2,"losses":0,"win_pct":1.0,"net_rating_avg":33.668893678193754,"off_rating_avg":110.27499006099083,"def_rating_avg":76.60609638279709,"pace_avg":80.34,"efg_pct_off_avg":0.5467263037685572,"tov_pct_off_avg":0.18141497570492143,"orb_pct_off_avg":0.33658076681332494},{"team_key":"CDP","opp_team_key":"SCL","team_name":"CD Póvoa / Esc Online","opponent_name":"Sport Club Lusitânia","games":2,"wins":2,"losses":0,"win_pct":1.0,"net_rating_avg":19.028757978991116,"off_rating_avg":110.02770673486788,"def_rating_avg":90.99894875587675,"pace_avg":78.67999999999999,"efg_pct_off_avg":0.5495238095238095,"tov_pct_off_avg":0.2155264279624894,"orb_pct_off_avg":0.38372859025032935},{"team_key":"CDP","opp_team_key":"SDC","team_name":"CD Póvoa / Esc Online","opponent_name":"Sangalhos","games":2,"wins":2,"losses":0,"win_pct":1.0,"net_rating_avg":22.73666162073218,"off_rating_avg":107.68281918384899,"def_rating_avg":84.94615756311681,"pace_avg":75.37,"efg_pct_off_avg":0.5,"tov_pct_off_avg":0.18700631464590453,"orb_pct_off_avg":0.41562313655336913},{"team_key":"GAL","opp_team_key":"GIN","team_name":"Clube dos Galitos","opponent_name":"Casino Ginásio","games":1,"wins":0,"losses":1,"win_pct":0.0,"net_rating_avg":-5.431146697785479,"off_rating_avg":105.54737358861071,"def_rating_avg":110.97852028639619,"pace_avg":73.45777777777778,"efg_pct_off_avg":0.5373134328358209,"tov_pct_off_avg":0.2700049091801669,"orb_pct_off_avg":0.4166666666666667},{"team_key":"GCO","opp_team_key":"ADG","team_name":"Ginásio ANTRIX","opponent_name":"AD Galomar","games":1,"wins":0,"losses":1,"win_pct":0.0,"net_rating_avg":-3.1834318838401146,"off_rating_avg":91.79780639008108,"def_rating_avg":94.98123827392119,"pace_avg":84.58,"efg_pct_off_avg":0.4393939393939394,"tov_pct_off_avg":0.2145922746781116,"orb_pct_off_avg":0.2727272727272727},{"team_key":"GCO","opp_team_key":"BSA","team_name":"Ginásio ANTRIX","opponent_name":"BSA - GALP","games":2,"wins":2,"losses":0,"win_pct":1.0,"net_rating_avg":11.214958574019661,"off_rating_avg":97.19390918815014,"def_rating_avg":85.97895061413047,"pace_avg":82.52,"efg_pct_off_avg":0.5318181818181817,"tov_pct_off_avg":0.22119692436479765,"orb_pct_off_avg":0.21354166666666666},{"team_key":"GCO","opp_team_key":"CAB","team_name":"Ginásio ANTRIX","opponent_name":"CAB Madeira","games":2,"wins":0,"losses":2,"win_pct":0.0,"net_rating_avg":-15.110552856674992,"off_rating_avg":97.28518733961815,"def_rating_avg":112.39574019629315,"pace_avg":74.92000000000002,"efg_pct_off_avg":0.5106268496099005,"tov_pct_off_avg":0.21971549371985943,"orb_pct_off_avg":0.28095238095238095},{"team_key":"GCO","opp_team_key":"CBQ","team_name":"Ginásio ANTRIX","opponent_name":"Clube Basket de Queluz","games":2,"wins":2,"losses":0,"win_pct":1.0,"net_rating_avg":33.440125151355616,"off_rating_avg":114.69808124921951,"def_rating_avg":81.25795609786388,"pace_avg":79.22999999999999,"efg_pct_off_avg":0.5888165281832473,"tov_pct_off_avg":0.18815506897406897,"orb_pct_off_avg":0.29702194357366773},{"team_key":"GCO","opp_team_key":"CDP","team_name":"Ginásio ANTRIX","opponent_name":"CD Póvoa / Esc Online","games":2,"wins":0,"losses":2,"win_pct":0.0,"net_rating_avg":-26.32694384832609,"off_rating_avg":77.29899953899303,"def_rating_avg":103.62594338731911,"pace_avg":80.93,"efg_pct_off_avg":0.40251782531194297,"tov_pct_off_avg":0.22529225565207822,"orb_pct_off_avg":0.24157801418439717},{"team_key":"GCO","opp_team_key":"GIN","team_name":"Ginásio ANTRIX","opponent_name":"Casino Ginásio","games":2,"wins":0,"losses":2,"win_pct":0.0,"net_rating_avg":-14.176277155762648,"off_rating_avg":90.55186108158034,"def_rating_avg":104.72813823734299,"pace_avg":77.15,"efg_pct_off_avg":0.4473684210526316,"tov_pct_off_avg":0.19740166256692693,"orb_pct_off_avg":0.2760910815939279},{"team_key":"GCO","opp_team_key":"IBC","team_name":"Ginásio ANTRIX","opponent_name":"Imortal LUZiGÁS","games":4,"wins":3,"losses":1,"win_pct":0.75,"net_rating_avg":16.71545393184637,"off_rating_avg":102.51397327481826,"def_rating_avg":85.79851934297189,"pace_avg":82.22111111111111,"efg_pct_off_avg":0.48684824807115834,"tov_pct_off_avg":0.1634636673274914,"orb_pct_off_avg":0.25486859039490617},{"team_key":"GCO","opp_team_key":"ILL","team_name":"Ginásio ANTRIX","opponent_name":"Illiabum MARGRES","games":2,"wins":0,"losses":2,"win_pct":0.0,"net_rating_avg":-16.986543077727298,"off_rating_avg":87.8993472560415,"def_rating_avg":104.88589033376878,"pace_avg":76.64,"efg_pct_off_avg":0.45019807583474813,"tov_pct_off_avg":0.19756049748186422,"orb_pct_off_avg":0.1935173299101412},{"team_key":"GCO","opp_team_key":"MBC","team_name":"Ginásio ANTRIX","opponent_name":"Maia Basket Clube","games":1,"wins":0,"losses":1,"win_pct":0.0,"net_rating_avg":-30.49670835268293,"off_rating_avg":87.16523496715513,"def_rating_avg":117.66194331983806,"pace_avg":79.1,"efg_pct_off_avg":0.4765625,"tov_pct_off_avg":0.202122283981809,"orb_pct_off_avg":0.17073170731707318},{"team_key":"GCO","opp_team_key":"PSC","team_name":"Ginásio ANTRIX","opponent_name":"Portimonense SC","games":4,"wins":1,"losses":3,"win_pct":0.25,"net_rating_avg":-8.844048002758594,"off_rating_avg":100.87080399367474,"def_rating_avg":109.71485199643334,"pace_avg":80.38,"efg_pct_off_avg":0.46865079365079365,"tov_pct_off_avg":0.1693346734028916,"orb_pct_off_avg":0.3147289624800311},{"team_key":"GCO","opp_team_key":"SLB","team_name":"Ginásio ANTRIX","opponent_name":"SL Benfica","games":2,"wins":1,"losses":1,"win_pct":0.5,"net_rating_avg":-0.4610796973900051,"off_rating_avg":87.66817689044298,"def_rating_avg":88.12925658783298,"pace_avg":84.0,"efg_pct_off_avg":0.5116479723899914,"tov_pct_off_avg":0.30705794622099397,"orb_pct_off_avg":0.2850174216027875},{"team_key":"GIN","opp_team_key":"AAC","team_name":"Casino Ginásio","opponent_name":"Académica Efapel","games":2,"wins":2,"losses":0,"win_pct":1.0,"net_rating_avg":23.082404545142154,"off_rating_avg":115.1496353635722,"def_rating_avg":92.06723081843005,"pace_avg":76.23,"efg_pct_off_avg":0.6335593220338983,"tov_pct_off_avg":0.24321697827864722,"orb_pct_off_avg":0.31481481481481477},{"team_key":"GIN","opp_team_key":"CAB","team_name":"Casino Ginásio","opponent_name":"CAB Madeira","games":2,"wins":0,"losses":2,"win_pct":0.0,"net_rating_avg":-20.661216400732727,"off_rating_avg":103.37271911050337,"def_rating_avg":124.0339355112361,"pace_avg":76.52000000000001,"efg_pct_off_avg":0.5736979166666667,"tov_pct_off_avg":0.20818704408025818,"orb_pct_off_avg":0.19696969696969696},{"team_key":"GIN","opp_team_key":"CDP","team_name":"Casino Ginásio","opponent_name":"CD Póvoa / Esc Online","games":4,"wins":0,"losses":4,"win_pct":0.0,"net_rating_avg":-16.494503412880903,"off_rating_avg":94.82155080138973,"def_rating_avg":111.31605421427064,"pace_avg":79.005,"efg_pct_off_avg":0.45731770833333335,"tov_pct_off_avg":0.16293072645989112,"orb_pct_off_avg":0.23226773226773229},{"team_key":"GIN","opp_team_key":"GAL","team_name":"Casino Ginásio","opponent_name":"Clube dos Galitos","games":1,"wins":1,"losses":0,"win_pct":1.0,"net_rating_avg":5.431146697785479,"off_rating_avg":110.97852028639619,"def_rating_avg":105.54737358861071,"pace_avg":73.45777777777778,"efg_pct_off_avg":0.5675675675675675,"tov_pct_off_avg":0.11933174224343676,"orb_pct_off_avg":0.23684210526315788},{"team_key":"GIN","opp_team_key":"GCO","team_name":"Casino Ginásio","opponent_name":"Ginásio ANTRIX","games":2,"wins":2,"losses":0,"win_pct":1.0,"net_rating_avg":14.176277155762648,"off_rating_avg":104.72813823734299,"def_rating_avg":90.55186108158034,"pace_avg":77.15,"efg_pct_off_avg":0.46086807928913187,"tov_pct_off_avg":0.14334595680975437,"orb_pct_off_avg":0.3632850241545894},{"team_key":"GIN","opp_team_key":"IBC","team_name":"Casino Ginásio","opponent_name":"Imortal LUZiGÁS","games":1,"wins":0,"losses":1,"win_pct":0.0,"net_rating_avg":-9.324054688811856,"off_rating_avg":83.80608561113976,"def_rating_avg":93.13014029995162,"pace_avg":80.12,"efg_pct_off_avg":0.4,"tov_pct_off_avg":0.27075812274368233,"orb_pct_off_avg":0.34146341463414637},{"team_key":"GIN","opp_team_key":"ILL","team_name":"Casino Ginásio","opponent_name":"Illiabum MARGRES","games":3,"wins":1,"losses":2,"win_pct":0.3333333333333333,"net_rating_avg":-13.60701566667242,"off_rating_avg":94.59554508828592,"def_rating_avg":108.20256075495833,"pace_avg":75.07333333333334,"efg_pct_off_avg":0.45372960372960375,"tov_pct_off_avg":0.1861017056783458,"orb_pct_off_avg":0.25544295521412225},{"team_key":"GIN","opp_team_key":"MBC","team_name":"Casino Ginásio","opponent_name":"Maia Basket Clube","games":4,"wins":1,"losses":3,"win_pct":0.25,"net_rating_avg":-16.918731759266326,"off_rating_avg":95.20097500280667,"def_rating_avg":112.119706762073,"pace_avg":81.905,"efg_pct_off_avg":0.4927554751554911,"tov_pct_off_avg":0.23192855312132066,"orb_pct_off_avg":0.31635636710824677},{"team_key":"GIN","opp_team_key":"PSC","team_name":"Casino Ginásio","opponent_name":"Portimonense SC","games":2,"wins":1,"losses":1,"win_pct":0.5,"net_rating_avg":1.9757098622312341,"off_rating_avg":111.38717395305258,"def_rating_avg":109.41146409082135,"pace_avg":74.78999999999999,"efg_pct_off_avg":0.5366931352459017,"tov_pct_off_avg":0.1366122667508001,"orb_pct_off_avg":0.23968705547652916},{"team_key":"GIN","opp_team_key":"SBC","team_name":"Casino Ginásio","opponent_name":"Sampaense Inspecentro","games":2,"wins":1,"losses":1,"win_pct":0.5,"net_rating_avg":-1.950875612462923,"off_rating_avg":105.45558147951365,"def_rating_avg":107.40645709197659,"pace_avg":67.82777777777778,"efg_pct_off_avg":0.5302823315118397,"tov_pct_off_avg":0.18687965379965657,"orb_pct_off_avg":0.22903225806451613},{"team_key":"GIN","opp_team_key":"SCL","team_name":"Casino Ginásio","opponent_name":"Sport Club Lusitânia","games":2,"wins":2,"losses":0,"win_pct":1.0,"net_rating_avg":7.615420902281279,"off_rating_avg":107.51706348300499,"def_rating_avg":99.90164258072372,"pace_avg":74.47,"efg_pct_off_avg":0.5601328434143584,"tov_pct_off_avg":0.2393918103736169,"orb_pct_off_avg":0.32447817836812143},{"team_key":"GIN","opp_team_key":"SDC","team_name":"Casino Ginásio","opponent_name":"Sangalhos","games":2,"wins":2,"losses":0,"win_pct":1.0,"net_rating_avg":13.55857713516641,"off_rating_avg":108.50312453668215,"def_rating_avg":94.94454740151575,"pace_avg":67.25,"efg_pct_off_avg":0.5777629233511586,"tov_pct_off_avg":0.218015690505257,"orb_pct_off_avg":0.3205128205128205},{"team_key":"IBC","opp_team_key":"ADG","team_name":"Imortal LUZiGÁS","opponent_name":"AD Galomar","games":2,"wins":2,"losses":0,"win_pct":1.0,"net_rating_avg":5.929289264644339,"off_rating_avg":107.98194152224177,"def_rating_avg":102.05265225759743,"pace_avg":80.31888888888889,"efg_pct_off_avg":0.5234375,"tov_pct_off_avg":0.18324727654628858,"orb_pct_off_avg":0.3121621621621622},{"team_key":"IBC","opp_team_key":"BSA","team_name":"Imortal LUZiGÁS","opponent_name":"BSA - GALP","games":2,"wins":2,"losses":0,"win_pct":1.0,"net_rating_avg":14.129320920341229,"off_rating_avg":111.48979529374557,"def_rating_avg":97.36047437340434,"pace_avg":77.82,"efg_pct_off_avg":0.5746584699453552,"tov_pct_off_avg":0.20231193601207936,"orb_pct_off_avg":0.25223214285714285},{"team_key":"IBC","opp_team_key":"CAB","team_name":"Imortal LUZiGÁS","opponent_name":"CAB Madeira","games":3,"wins":0,"losses":3,"win_pct":0.0,"net_rating_avg":-14.264110949259873,"off_rating_avg":94.21022259275958,"def_rating_avg":108.47433354201945,"pace_avg":77.80666666666666,"efg_pct_off_avg":0.4329115914679476,"tov_pct_off_avg":0.20594497890449784,"orb_pct_off_avg":0.27126352658267555},{"team_key":"IBC","opp_team_key":"CBQ","team_name":"Imortal LUZiGÁS","opponent_name":"Clube Basket de Queluz","games":2,"wins":2,"losses":0,"win_pct":1.0,"net_rating_avg":7.337023601153106,"off_rating_avg":106.83617321146754,"def_rating_avg":99.49914961031443,"pace_avg":75.95,"efg_pct_off_avg":0.5072280178837556,"tov_pct_off_avg":0.22542851355799173,"orb_pct_off_avg":0.35378787878787876},{"team_key":"IBC","opp_team_key":"CDP","team_name":"Imortal LUZiGÁS","opponent_name":"CD Póvoa / Esc Online","games":2,"wins":0,"losses":2,"win_pct":0.0,"net_rating_avg":-33.67300681089325,"off_rating_avg":79.42034875129303,"def_rating_avg":113.09335556218629,"pace_avg":79.87,"efg_pct_off_avg":0.42481740234995236,"tov_pct_off_avg":0.3101756071129501,"orb_pct_off_avg":0.31770833333333337},{"team_key":"IBC","opp_team_key":"GCO","team_name":"Imortal LUZiGÁS","opponent_name":"Ginásio ANTRIX","games":4,"wins":1,"losses":3,"win_pct":0.25,"net_rating_avg":-16.71545393184637,"off_rating_avg":85.79851934297189,"def_rating_avg":102.51397327481826,"pace_avg":82.22111111111111,"efg_pct_off_avg":0.3730222907438097,"tov_pct_off_avg":0.19026093213154166,"orb_pct_off_avg":0.30842322571045977},{"team_key":"IBC","opp_team_key":"GIN","team_name":"Imortal LUZiGÁS","opponent_name":"Casino Ginásio","games":1,"wins":1,"losses":0,"win_pct":1.0,"net_rating_avg":9.324054688811856,"off_rating_avg":93.13014029995162,"def_rating_avg":83.80608561113976,"pace_avg":80.12,"efg_pct_off_avg":0.4357142857142857,"tov_pct_off_avg":0.21770682148040638,"orb_pct_off_avg":0.32608695652173914},{"team_key":"IBC","opp_team_key":"ILL","team_name":"Imortal LUZiGÁS","opponent_name":"Illiabum MARGRES","games":1,"wins":1,"losses":0,"win_pct":1.0,"net_rating_avg":1.3495387031341863,"off_rating_avg":109.10815939278937,"def_rating_avg":107.75862068965519,"pace_avg":74.59555555555553,"efg_pct_off_avg":0.4791666666666667,"tov_pct_off_avg":0.18975332068311196,"orb_pct_off_avg":0.36363636363636365},{"team_key":"IBC","opp_team_key":"MBC","team_name":"Imortal LUZiGÁS","opponent_name":"Maia Basket Clube","games":2,"wins":1,"losses":1,"win_pct":0.5,"net_rating_avg":-14.194953255760794,"off_rating_avg":84.86472690148034,"def_rating_avg":99.05968015724113,"pace_avg":78.77000000000001,"efg_pct_off_avg":0.4596516690856314,"tov_pct_off_avg":0.2552322613578356,"orb_pct_off_avg":0.23817567567567569},{"team_key":"IBC","opp_team_key":"PSC","team_name":"Imortal LUZiGÁS","opponent_name":"Portimonense SC","games":4,"wins":1,"losses":3,"win_pct":0.25,"net_rating_avg":-3.064181268511316,"off_rating_avg":98.17169536588776,"def_rating_avg":101.23587663439908,"pace_avg":76.47111111111111,"efg_pct_off_avg":0.47666254497493044,"tov_pct_off_avg":0.20407520087460146,"orb_pct_off_avg":0.3337627923976608},{"team_key":"IBC","opp_team_key":"SLB","team_name":"Imortal LUZiGÁS","opponent_name":"SL Benfica","games":2,"wins":2,"losses":0,"win_pct":1.0,"net_rating_avg":20.47419333954808,"off_rating_avg":101.373591208041,"def_rating_avg":80.89939786849294,"pace_avg":78.4,"efg_pct_off_avg":0.4340686274509804,"tov_pct_off_avg":0.20812507492223326,"orb_pct_off_avg":0.37493540051679586},{"team_key":"ILL","opp_team_key":"AAC","team_name":"Illiabum Clube","opponent_name":"Académica Efapel","games":2,"wins":2,"losses":0,"win_pct":1.0,"net_rating_avg":39.85743457735377,"off_rating_avg":106.68553581108708,"def_rating_avg":66.8281012337333,"pace_avg":77.75999999999999,"efg_pct_off_avg":0.5047603765511339,"tov_pct_off_avg":0.2451003154085306,"orb_pct_off_avg":0.48511904761904756},{"team_key":"ILL","opp_team_key":"CAB","team_name":"Illiabum MARGRES","opponent_name":"CAB Madeira","games":2,"wins":0,"losses":2,"win_pct":0.0,"net_rating_avg":-5.062054382020754,"off_rating_avg":88.34935940721533,"def_rating_avg":93.4114137892361,"pace_avg":72.64,"efg_pct_off_avg":0.40507246376811595,"tov_pct_off_avg":0.1983789356165987,"orb_pct_off_avg":0.3258236434108527},{"team_key":"ILL","opp_team_key":"CDP","team_name":"Illiabum MARGRES","opponent_name":"CD Póvoa / Esc Online","games":4,"wins":0,"losses":4,"win_pct":0.0,"net_rating_avg":-19.21268079467704,"off_rating_avg":79.04193545131334,"def_rating_avg":98.25461624599038,"pace_avg":76.635,"efg_pct_off_avg":0.396376980247948,"tov_pct_off_avg":0.24804721967104945,"orb_pct_off_avg":0.27474937343358397},{"team_key":"ILL","opp_team_key":"GCO","team_name":"Illiabum MARGRES","opponent_name":"Ginásio ANTRIX","games":2,"wins":2,"losses":0,"win_pct":1.0,"net_rating_avg":16.986543077727298,"off_rating_avg":104.88589033376878,"def_rating_avg":87.8993472560415,"pace_avg":76.64,"efg_pct_off_avg":0.5020634920634921,"tov_pct_off_avg":0.19640479091470886,"orb_pct_off_avg":0.3916083916083916},{"team_key":"ILL","opp_team_key":"GIN","team_name":"Illiabum MARGRES","opponent_name":"Casino Ginásio","games":3,"wins":2,"losses":1,"win_pct":0.6666666666666666,"net_rating_avg":13.60701566667242,"off_rating_avg":108.20256075495833,"def_rating_avg":94.59554508828592,"pace_avg":75.07333333333334,"efg_pct_off_avg":0.6053445677771166,"tov_pct_off_avg":0.25618017272754406,"orb_pct_off_avg":0.3065953654188948},{"team_key":"ILL","opp_team_key":"IBC","team_name":"Illiabum MARGRES","opponent_name":"Imortal LUZiGÁS","games":1,"wins":0,"losses":1,"win_pct":0.0,"net_rating_avg":-1.3495387031341863,"off_rating_avg":107.75862068965519,"def_rating_avg":109.10815939278937,"pace_avg":74.59555555555553,"efg_pct_off_avg":0.515625,"tov_pct_off_avg":0.19157088122605365,"orb_pct_off_avg":0.28205128205128205},{"team_key":"ILL","opp_team_key":"MBC","team_name":"Illiabum MARGRES","opponent_name":"Maia Basket Clube","games":4,"wins":3,"losses":1,"win_pct":0.75,"net_rating_avg":4.453911541461672,"off_rating_avg":100.78263803026448,"def_rating_avg":96.3287264888028,"pace_avg":75.795,"efg_pct_off_avg":0.439258658008658,"tov_pct_off_avg":0.1902561413888208,"orb_pct_off_avg":0.3247270309627289},{"team_key":"ILL","opp_team_key":"PSC","team_name":"Illiabum MARGRES","opponent_name":"Portimonense SC","games":1,"wins":1,"losses":0,"win_pct":1.0,"net_rating_avg":5.3462206584600125,"off_rating_avg":90.70576540755468,"def_rating_avg":85.35954474909467,"pace_avg":78.9,"efg_pct_off_avg":0.3918918918918919,"tov_pct_off_avg":0.22365805168986083,"orb_pct_off_avg":0.40425531914893614},{"team_key":"ILL","opp_team_key":"SBC","team_name":"Illiabum Clube","opponent_name":"Sampaense Inspecentro","games":2,"wins":2,"losses":0,"win_pct":1.0,"net_rating_avg":8.162844417559256,"off_rating_avg":115.26860298538045,"def_rating_avg":107.1057585678212,"pace_avg":68.65333333333334,"efg_pct_off_avg":0.5813061872025383,"tov_pct_off_avg":0.19120843080579128,"orb_pct_off_avg":0.3529411764705882},{"team_key":"ILL","opp_team_key":"SCL","team_name":"Illiabum Clube","opponent_name":"Sport Club Lusitânia","games":2,"wins":2,"losses":0,"win_pct":1.0,"net_rating_avg":13.888693048029829,"off_rating_avg":97.95981333641868,"def_rating_avg":84.07112028838884,"pace_avg":75.22,"efg_pct_off_avg":0.47720539828834757,"tov_pct_off_avg":0.2660470258526489,"orb_pct_off_avg":0.37683823529411764},{"team_key":"ILL","opp_team_key":"SDC","team_name":"Illiabum Clube","opponent_name":"Sangalhos","games":2,"wins":2,"losses":0,"win_pct":1.0,"net_rating_avg":32.155848598525075,"off_rating_avg":121.96561765527284,"def_rating_avg":89.80976905674775,"pace_avg":78.62,"efg_pct_off_avg":0.619641192917055,"tov_pct_off_avg":0.21139870277801312,"orb_pct_off_avg":0.42841880341880345},{"team_key":"MBC","opp_team_key":"AAC","team_name":"Maia Basket Clube","opponent_name":"Académica Efapel","games":2,"wins":2,"losses":0,"win_pct":1.0,"net_rating_avg":35.08763479438996,"off_rating_avg":104.19933200092416,"def_rating_avg":69.11169720653419,"pace_avg":85.31,"efg_pct_off_avg":0.5330209241499564,"tov_pct_off_avg":0.32588227245300116,"orb_pct_off_avg":0.5223684210526316},{"team_key":"MBC","opp_team_key":"CAB","team_name":"Maia Basket Clube","opponent_name":"CAB Madeira","games":2,"wins":2,"losses":0,"win_pct":1.0,"net_rating_avg":8.975651529847624,"off_rating_avg":109.23116812238953,"def_rating_avg":100.25551659254191,"pace_avg":81.24111111111111,"efg_pct_off_avg":0.4503065664556962,"tov_pct_off_avg":0.16926613550082192,"orb_pct_off_avg":0.3674953095684803},{"team_key":"MBC","opp_team_key":"CDP","team_name":"Maia Basket Clube","opponent_name":"CD Póvoa / Esc Online","games":3,"wins":0,"losses":3,"win_pct":0.0,"net_rating_avg":-20.62182916209066,"off_rating_avg":87.80223783526701,"def_rating_avg":108.42406699735766,"pace_avg":84.13333333333333,"efg_pct_off_avg":0.43185972533798617,"tov_pct_off_avg":0.24330238197875773,"orb_pct_off_avg":0.36871403720058876},{"team_key":"MBC","opp_team_key":"GCO","team_name":"Maia Basket Clube","opponent_name":"Ginásio ANTRIX","games":1,"wins":1,"losses":0,"win_pct":1.0,"net_rating_avg":30.49670835268293,"off_rating_avg":117.66194331983806,"def_rating_avg":87.16523496715513,"pace_avg":79.1,"efg_pct_off_avg":0.5131578947368421,"tov_pct_off_avg":0.24038461538461536,"orb_pct_off_avg":0.575},{"team_key":"MBC","opp_team_key":"GIN","team_name":"Maia Basket Clube","opponent_name":"Casino Ginásio","games":4,"wins":3,"losses":1,"win_pct":0.75,"net_rating_avg":16.918731759266326,"off_rating_avg":112.119706762073,"def_rating_avg":95.20097500280667,"pace_avg":81.905,"efg_pct_off_avg":0.5735998393027306,"tov_pct_off_avg":0.17488136709783447,"orb_pct_off_avg":0.2321105072463768},{"team_key":"MBC","opp_team_key":"IBC","team_name":"Maia Basket Clube","opponent_name":"Imortal LUZiGÁS","games":2,"wins":1,"losses":1,"win_pct":0.5,"net_rating_avg":14.194953255760794,"off_rating_avg":99.05968015724113,"def_rating_avg":84.86472690148034,"pace_avg":78.77000000000001,"efg_pct_off_avg":0.4256410256410257,"tov_pct_off_avg":0.20890288573215404,"orb_pct_off_avg":0.40731707317073174},{"team_key":"MBC","opp_team_key":"ILL","team_name":"Maia Basket Clube","opponent_name":"Illiabum MARGRES","games":4,"wins":1,"losses":3,"win_pct":0.25,"net_rating_avg":-4.453911541461672,"off_rating_avg":96.3287264888028,"def_rating_avg":100.78263803026448,"pace_avg":75.795,"efg_pct_off_avg":0.42233589087809037,"tov_pct_off_avg":0.19990128397960463,"orb_pct_off_avg":0.3644036028946515},{"team_key":"MBC","opp_team_key":"PSC","team_name":"Maia Basket Clube","opponent_name":"Portimonense SC","games":2,"wins":1,"losses":1,"win_pct":0.5,"net_rating_avg":2.572915892660788,"off_rating_avg":94.34085840593791,"def_rating_avg":91.76794251327712,"pace_avg":77.33,"efg_pct_off_avg":0.4112676056338028,"tov_pct_off_avg":0.15916397443897662,"orb_pct_off_avg":0.3111111111111111},{"team_key":"MBC","opp_team_key":"SBC","team_name":"Maia Basket Clube","opponent_name":"Sampaense Inspecentro","games":2,"wins":2,"losses":0,"win_pct":1.0,"net_rating_avg":15.870944173242833,"off_rating_avg":107.30711737987316,"def_rating_avg":91.43617320663033,"pace_avg":73.88,"efg_pct_off_avg":0.5106736242884251,"tov_pct_off_avg":0.1868147304390437,"orb_pct_off_avg":0.36403508771929827},{"team_key":"MBC","opp_team_key":"SCL","team_name":"Maia Basket Clube","opponent_name":"Sport Club Lusitânia","games":2,"wins":1,"losses":1,"win_pct":0.5,"net_rating_avg":-1.3078581229409494,"off_rating_avg":102.48769637763624,"def_rating_avg":103.79555450057718,"pace_avg":73.15,"efg_pct_off_avg":0.4855769230769231,"tov_pct_off_avg":0.24238875012931738,"orb_pct_off_avg":0.3573232323232323},{"team_key":"MBC","opp_team_key":"SDC","team_name":"Maia Basket Clube","opponent_name":"Sangalhos","games":2,"wins":2,"losses":0,"win_pct":1.0,"net_rating_avg":53.17262283277436,"off_rating_avg":129.813476589824,"def_rating_avg":76.64085375704965,"pace_avg":82.36000000000001,"efg_pct_off_avg":0.6143177809844477,"tov_pct_off_avg":0.1857562785130757,"orb_pct_off_avg":0.4825581395348837},{"team_key":"PSC","opp_team_key":"ADG","team_name":"Portimonense SC","opponent_name":"AD Galomar","games":2,"wins":1,"losses":1,"win_pct":0.5,"net_rating_avg":-1.3915980137677764,"off_rating_avg":111.93649075246967,"def_rating_avg":113.32808876623744,"pace_avg":74.83,"efg_pct_off_avg":0.5800438596491229,"tov_pct_off_avg":0.2171497485408269,"orb_pct_off_avg":0.2897465437788018},{"team_key":"PSC","opp_team_key":"BSA","team_name":"Portimonense SC","opponent_name":"BSA - GALP","games":2,"wins":2,"losses":0,"win_pct":1.0,"net_rating_avg":25.547721434117392,"off_rating_avg":110.70666236609063,"def_rating_avg":85.15894093197323,"pace_avg":78.78999999999999,"efg_pct_off_avg":0.5635627530364373,"tov_pct_off_avg":0.22131509800074572,"orb_pct_off_avg":0.35317460317460314},{"team_key":"PSC","opp_team_key":"CAB","team_name":"Portimonense SC","opponent_name":"CAB Madeira","games":4,"wins":2,"losses":2,"win_pct":0.5,"net_rating_avg":-0.42239413512751867,"off_rating_avg":102.91114316297265,"def_rating_avg":103.33353729810017,"pace_avg":72.18777777777778,"efg_pct_off_avg":0.48452998574026773,"tov_pct_off_avg":0.20107500684042134,"orb_pct_off_avg":0.3432636469221835},{"team_key":"PSC","opp_team_key":"CBQ","team_name":"Portimonense SC","opponent_name":"Clube Basket de Queluz","games":2,"wins":2,"losses":0,"win_pct":1.0,"net_rating_avg":27.634397230543968,"off_rating_avg":110.1508656917129,"def_rating_avg":82.51646846116893,"pace_avg":76.10999999999999,"efg_pct_off_avg":0.536472148541114,"tov_pct_off_avg":0.20876407799630192,"orb_pct_off_avg":0.36403508771929827},{"team_key":"PSC","opp_team_key":"CDP","team_name":"Portimonense SC","opponent_name":"CD Póvoa / Esc Online","games":1,"wins":1,"losses":0,"win_pct":1.0,"net_rating_avg":5.751161897094335,"off_rating_avg":94.95192307692307,"def_rating_avg":89.20076117982873,"pace_avg":74.34666666666666,"efg_pct_off_avg":0.5083333333333333,"tov_pct_off_avg":0.20432692307692307,"orb_pct_off_avg":0.175},{"team_key":"PSC","opp_team_key":"GCO","team_name":"Portimonense SC","opponent_name":"Ginásio ANTRIX","games":4,"wins":3,"losses":1,"win_pct":0.75,"net_rating_avg":8.844048002758594,"off_rating_avg":109.71485199643334,"def_rating_avg":100.87080399367474,"pace_avg":80.38,"efg_pct_off_avg":0.5438973649227755,"tov_pct_off_avg":0.21185137305744392,"orb_pct_off_avg":0.32995010504201683},{"team_key":"PSC","opp_team_key":"GIN","team_name":"Portimonense SC","opponent_name":"Casino Ginásio","games":2,"wins":1,"losses":1,"win_pct":0.5,"net_rating_avg":-1.9757098622312341,"off_rating_avg":109.41146409082135,"def_rating_avg":111.38717395305258,"pace_avg":74.78999999999999,"efg_pct_off_avg":0.5769434161819144,"tov_pct_off_avg":0.22201970486568057,"orb_pct_off_avg":0.34895833333333337},{"team_key":"PSC","opp_team_key":"IBC","team_name":"Portimonense SC","opponent_name":"Imortal LUZiGÁS","games":4,"wins":3,"losses":1,"win_pct":0.75,"net_rating_avg":3.064181268511316,"off_rating_avg":101.23587663439908,"def_rating_avg":98.17169536588776,"pace_avg":76.47111111111111,"efg_pct_off_avg":0.5086569924598093,"tov_pct_off_avg":0.24377499597536526,"orb_pct_off_avg":0.3386769290890401},{"team_key":"PSC","opp_team_key":"ILL","team_name":"Portimonense SC","opponent_name":"Illiabum MARGRES","games":1,"wins":0,"losses":1,"win_pct":0.0,"net_rating_avg":-5.3462206584600125,"off_rating_avg":85.35954474909467,"def_rating_avg":90.70576540755468,"pace_avg":78.9,"efg_pct_off_avg":0.3898305084745763,"tov_pct_off_avg":0.27159855147439216,"orb_pct_off_avg":0.39473684210526316},{"team_key":"PSC","opp_team_key":"MBC","team_name":"Portimonense SC","opponent_name":"Maia Basket Clube","games":2,"wins":1,"losses":1,"win_pct":0.5,"net_rating_avg":-2.572915892660788,"off_rating_avg":91.76794251327712,"def_rating_avg":94.34085840593791,"pace_avg":77.33,"efg_pct_off_avg":0.5164452877925364,"tov_pct_off_avg":0.2886252553711103,"orb_pct_off_avg":0.2912280701754386},{"team_key":"PSC","opp_team_key":"SLB","team_name":"Portimonense SC","opponent_name":"SL Benfica","games":2,"wins":1,"losses":1,"win_pct":0.5,"net_rating_avg":6.343055542997526,"off_rating_avg":96.41379300797274,"def_rating_avg":90.07073746497521,"pace_avg":76.34,"efg_pct_off_avg":0.4559134906231095,"tov_pct_off_avg":0.24969647131463568,"orb_pct_off_avg":0.34460887949260044},{"team_key":"SBC","opp_team_key":"AAC","team_name":"Sampaense Inspecentro","opponent_name":"Académica Efapel","games":3,"wins":2,"losses":1,"win_pct":0.6666666666666666,"net_rating_avg":14.749009695268251,"off_rating_avg":99.65722721082007,"def_rating_avg":84.90821751555181,"pace_avg":72.59333333333332,"efg_pct_off_avg":0.489033189033189,"tov_pct_off_avg":0.18832509670001193,"orb_pct_off_avg":0.28156431761946077},{"team_key":"SBC","opp_team_key":"BSA","team_name":"Sampaense Inspecentro","opponent_name":"BSA - GALP","games":1,"wins":0,"losses":1,"win_pct":0.0,"net_rating_avg":-32.2933226034129,"off_rating_avg":66.44085461177697,"def_rating_avg":98.73417721518987,"pace_avg":77.88,"efg_pct_off_avg":0.28846153846153844,"tov_pct_off_avg":0.2344971339239187,"orb_pct_off_avg":0.13953488372093023},{"team_key":"SBC","opp_team_key":"CBQ","team_name":"Sampaense Inspecentro","opponent_name":"Clube Basket de Queluz","games":2,"wins":1,"losses":1,"win_pct":0.5,"net_rating_avg":-6.345343787564005,"off_rating_avg":102.17727892613213,"def_rating_avg":108.52262271369614,"pace_avg":68.99000000000001,"efg_pct_off_avg":0.47669220945083013,"tov_pct_off_avg":0.1617690981223091,"orb_pct_off_avg":0.2954545454545454},{"team_key":"SBC","opp_team_key":"CDP","team_name":"Sampaense Inspecentro","opponent_name":"CD Póvoa / Esc Online","games":2,"wins":0,"losses":2,"win_pct":0.0,"net_rating_avg":-33.668893678193754,"off_rating_avg":76.60609638279709,"def_rating_avg":110.27499006099083,"pace_avg":80.34,"efg_pct_off_avg":0.4018218623481782,"tov_pct_off_avg":0.2617586095169616,"orb_pct_off_avg":0.24404761904761904},{"team_key":"SBC","opp_team_key":"GIN","team_name":"Sampaense Inspecentro","opponent_name":"Casino Ginásio","games":2,"wins":1,"losses":1,"win_pct":0.5,"net_rating_avg":1.950875612462923,"off_rating_avg":107.40645709197659,"def_rating_avg":105.45558147951365,"pace_avg":67.82777777777778,"efg_pct_off_avg":0.535169256381798,"tov_pct_off_avg":0.16088794055953648,"orb_pct_off_avg":0.2376395534290271},{"team_key":"SBC","opp_team_key":"ILL","team_name":"Sampaense Inspecentro","opponent_name":"Illiabum Clube","games":2,"wins":0,"losses":2,"win_pct":0.0,"net_rating_avg":-8.162844417559256,"off_rating_avg":107.1057585678212,"def_rating_avg":115.26860298538045,"pace_avg":68.65333333333334,"efg_pct_off_avg":0.5567502986857826,"tov_pct_off_avg":0.1737310671934293,"orb_pct_off_avg":0.22478991596638653},{"team_key":"SBC","opp_team_key":"MBC","team_name":"Sampaense Inspecentro","opponent_name":"Maia Basket Clube","games":2,"wins":0,"losses":2,"win_pct":0.0,"net_rating_avg":-15.870944173242833,"off_rating_avg":91.43617320663033,"def_rating_avg":107.30711737987316,"pace_avg":73.88,"efg_pct_off_avg":0.42824543610547666,"tov_pct_off_avg":0.22263217512030842,"orb_pct_off_avg":0.3312135665076842},{"team_key":"SBC","opp_team_key":"SCL","team_name":"Sampaense Inspecentro","opponent_name":"Sport Club Lusitânia","games":4,"wins":1,"losses":3,"win_pct":0.25,"net_rating_avg":-23.42561682893019,"off_rating_avg":89.28224075823252,"def_rating_avg":112.70785758716269,"pace_avg":75.21,"efg_pct_off_avg":0.46999997234574453,"tov_pct_off_avg":0.23105921839882826,"orb_pct_off_avg":0.2365709531041339},{"team_key":"SBC","opp_team_key":"SDC","team_name":"Sampaense Inspecentro","opponent_name":"Sangalhos","games":3,"wins":3,"losses":0,"win_pct":1.0,"net_rating_avg":10.209808717270112,"off_rating_avg":113.0979186923215,"def_rating_avg":102.88810997505136,"pace_avg":72.86,"efg_pct_off_avg":0.5776267094573105,"tov_pct_off_avg":0.17711374106760402,"orb_pct_off_avg":0.26504322158971116},{"team_key":"SBC","opp_team_key":"SLB","team_name":"Sampaense Inspecentro","opponent_name":"SL Benfica","games":2,"wins":1,"losses":1,"win_pct":0.5,"net_rating_avg":-3.2729600176651132,"off_rating_avg":97.16534480673198,"def_rating_avg":100.43830482439708,"pace_avg":68.87,"efg_pct_off_avg":0.43883914294851295,"tov_pct_off_avg":0.16104228223869507,"orb_pct_off_avg":0.24932065217391303},{"team_key":"SCL","opp_team_key":"AAC","team_name":"Sport Club Lusitânia","opponent_name":"Académica Efapel","games":3,"wins":3,"losses":0,"win_pct":1.0,"net_rating_avg":21.81255446502959,"off_rating_avg":110.97984835886501,"def_rating_avg":89.16729389383543,"pace_avg":77.72666666666667,"efg_pct_off_avg":0.5244897959183673,"tov_pct_off_avg":0.19978911626220955,"orb_pct_off_avg":0.41327785403797757},{"team_key":"SCL","opp_team_key":"ADG","team_name":"Sport Club Lusitânia","opponent_name":"AD Galomar","games":2,"wins":2,"losses":0,"win_pct":1.0,"net_rating_avg":12.29615096834393,"off_rating_avg":122.24986783382717,"def_rating_avg":109.95371686548324,"pace_avg":77.03,"efg_pct_off_avg":0.5968468468468469,"tov_pct_off_avg":0.15809994221571977,"orb_pct_off_avg":0.36813186813186816},{"team_key":"SCL","opp_team_key":"BSA","team_name":"Sport Club Lusitânia","opponent_name":"BSA - GALP","games":2,"wins":2,"losses":0,"win_pct":1.0,"net_rating_avg":8.178734621032852,"off_rating_avg":98.55081608615177,"def_rating_avg":90.37208146511892,"pace_avg":80.42,"efg_pct_off_avg":0.4691780821917808,"tov_pct_off_avg":0.21512704021537943,"orb_pct_off_avg":0.33756166314305847},{"team_key":"SCL","opp_team_key":"CBQ","team_name":"Sport Club Lusitânia","opponent_name":"Clube Basket de Queluz","games":1,"wins":1,"losses":0,"win_pct":1.0,"net_rating_avg":6.599548898524063,"off_rating_avg":107.23514211886305,"def_rating_avg":100.63559322033899,"pace_avg":76.46000000000001,"efg_pct_off_avg":0.48717948717948717,"tov_pct_off_avg":0.16795865633074933,"orb_pct_off_avg":0.42857142857142855},{"team_key":"SCL","opp_team_key":"CDP","team_name":"Sport Club Lusitânia","opponent_name":"CD Póvoa / Esc Online","games":2,"wins":0,"losses":2,"win_pct":0.0,"net_rating_avg":-19.028757978991116,"off_rating_avg":90.99894875587675,"def_rating_avg":110.02770673486788,"pace_avg":78.67999999999999,"efg_pct_off_avg":0.42820945945945943,"tov_pct_off_avg":0.22663675387092455,"orb_pct_off_avg":0.34954233409610985},{"team_key":"SCL","opp_team_key":"GIN","team_name":"Sport Club Lusitânia","opponent_name":"Casino Ginásio","games":2,"wins":0,"losses":2,"win_pct":0.0,"net_rating_avg":-7.615420902281279,"off_rating_avg":99.90164258072372,"def_rating_avg":107.51706348300499,"pace_avg":74.47,"efg_pct_off_avg":0.4423319327731092,"tov_pct_off_avg":0.1903790898273957,"orb_pct_off_avg":0.39625850340136054},{"team_key":"SCL","opp_team_key":"ILL","team_name":"Sport Club Lusitânia","opponent_name":"Illiabum Clube","games":2,"wins":0,"losses":2,"win_pct":0.0,"net_rating_avg":-13.888693048029829,"off_rating_avg":84.07112028838884,"def_rating_avg":97.95981333641868,"pace_avg":75.22,"efg_pct_off_avg":0.3783502472027062,"tov_pct_off_avg":0.22353724985250803,"orb_pct_off_avg":0.3395348837209302},{"team_key":"SCL","opp_team_key":"MBC","team_name":"Sport Club Lusitânia","opponent_name":"Maia Basket Clube","games":2,"wins":1,"losses":1,"win_pct":0.5,"net_rating_avg":1.3078581229409494,"off_rating_avg":103.79555450057718,"def_rating_avg":102.48769637763624,"pace_avg":73.15,"efg_pct_off_avg":0.440336044520548,"tov_pct_off_avg":0.1287588789937449,"orb_pct_off_avg":0.3519036954087346},{"team_key":"SCL","opp_team_key":"SBC","team_name":"Sport Club Lusitânia","opponent_name":"Sampaense Inspecentro","games":4,"wins":3,"losses":1,"win_pct":0.75,"net_rating_avg":23.42561682893019,"off_rating_avg":112.70785758716269,"def_rating_avg":89.28224075823252,"pace_avg":75.21,"efg_pct_off_avg":0.556572385947386,"tov_pct_off_avg":0.17389158474509603,"orb_pct_off_avg":0.2970517168554959},{"team_key":"SCL","opp_team_key":"SDC","team_name":"Sport Club Lusitânia","opponent_name":"Sangalhos","games":4,"wins":4,"losses":0,"win_pct":1.0,"net_rating_avg":22.466833019194713,"off_rating_avg":119.20044747544604,"def_rating_avg":96.73361445625133,"pace_avg":79.43833333333333,"efg_pct_off_avg":0.6163392186829687,"tov_pct_off_avg":0.23232617655440455,"orb_pct_off_avg":0.45930330634278},{"team_key":"SCL","opp_team_key":"SLB","team_name":"Sport Club Lusitânia","opponent_name":"SL Benfica","games":2,"wins":2,"losses":0,"win_pct":1.0,"net_rating_avg":12.726348788304172,"off_rating_avg":115.4513634155328,"def_rating_avg":102.72501462722862,"pace_avg":76.78,"efg_pct_off_avg":0.5431818181818182,"tov_pct_off_avg":0.20814788730098177,"orb_pct_off_avg":0.455982905982906},{"team_key":"SDC","opp_team_key":"AAC","team_name":"Sangalhos","opponent_name":"Académica Efapel","games":4,"wins":4,"losses":0,"win_pct":1.0,"net_rating_avg":8.018572092694349,"off_rating_avg":92.96713560882245,"def_rating_avg":84.9485635161281,"pace_avg":75.625,"efg_pct_off_avg":0.49623575665724917,"tov_pct_off_avg":0.2745804825389341,"orb_pct_off_avg":0.32465723131357804},{"team_key":"SDC","opp_team_key":"ADG","team_name":"Sangalhos","opponent_name":"AD Galomar","games":2,"wins":0,"losses":2,"win_pct":0.0,"net_rating_avg":-38.63002532145876,"off_rating_avg":89.62130787653007,"def_rating_avg":128.25133319798883,"pace_avg":79.07,"efg_pct_off_avg":0.4686185133239832,"tov_pct_off_avg":0.19243777337513307,"orb_pct_off_avg":0.2277777777777778},{"team_key":"SDC","opp_team_key":"BSA","team_name":"Sangalhos","opponent_name":"BSA - GALP","games":1,"wins":0,"losses":1,"win_pct":0.0,"net_rating_avg":-17.104560472580232,"off_rating_avg":107.60201229737282,"def_rating_avg":124.70657276995306,"pace_avg":69.86,"efg_pct_off_avg":0.4357142857142857,"tov_pct_off_avg":0.15371716042481834,"orb_pct_off_avg":0.4166666666666667},{"team_key":"SDC","opp_team_key":"CBQ","team_name":"Sangalhos","opponent_name":"Clube Basket de Queluz","games":2,"wins":0,"losses":2,"win_pct":0.0,"net_rating_avg":-26.417854771575684,"off_rating_avg":82.66360356375148,"def_rating_avg":109.08145833532717,"pace_avg":73.89,"efg_pct_off_avg":0.4829879369007114,"tov_pct_off_avg":0.2335990364876727,"orb_pct_off_avg":0.1752136752136752},{"team_key":"SDC","opp_team_key":"CDP","team_name":"Sangalhos","opponent_name":"CD Póvoa / Esc Online","games":2,"wins":0,"losses":2,"win_pct":0.0,"net_rating_avg":-22.73666162073218,"off_rating_avg":84.94615756311681,"def_rating_avg":107.68281918384899,"pace_avg":75.37,"efg_pct_off_avg":0.41082506203473945,"tov_pct_off_avg":0.2168935759990969,"orb_pct_off_avg":0.2788398154251813},{"team_key":"SDC","opp_team_key":"GIN","team_name":"Sangalhos","opponent_name":"Casino Ginásio","games":2,"wins":0,"losses":2,"win_pct":0.0,"net_rating_avg":-13.55857713516641,"off_rating_avg":94.94454740151575,"def_rating_avg":108.50312453668215,"pace_avg":67.25,"efg_pct_off_avg":0.46218487394957986,"tov_pct_off_avg":0.2026877203862212,"orb_pct_off_avg":0.29642857142857143},{"team_key":"SDC","opp_team_key":"ILL","team_name":"Sangalhos","opponent_name":"Illiabum Clube","games":2,"wins":0,"losses":2,"win_pct":0.0,"net_rating_avg":-32.155848598525075,"off_rating_avg":89.80976905674775,"def_rating_avg":121.96561765527284,"pace_avg":78.62,"efg_pct_off_avg":0.5088383838383839,"tov_pct_off_avg":0.21476012224461793,"orb_pct_off_avg":0.19210526315789472},{"team_key":"SDC","opp_team_key":"MBC","team_name":"Sangalhos","opponent_name":"Maia Basket Clube","games":2,"wins":0,"losses":2,"win_pct":0.0,"net_rating_avg":-53.17262283277436,"off_rating_avg":76.64085375704965,"def_rating_avg":129.813476589824,"pace_avg":82.36000000000001,"efg_pct_off_avg":0.3904903017241379,"tov_pct_off_avg":0.28842387073737263,"orb_pct_off_avg":0.2777777777777778},{"team_key":"SDC","opp_team_key":"SBC","team_name":"Sangalhos","opponent_name":"Sampaense Inspecentro","games":3,"wins":0,"losses":3,"win_pct":0.0,"net_rating_avg":-10.209808717270112,"off_rating_avg":102.88810997505136,"def_rating_avg":113.0979186923215,"pace_avg":72.86,"efg_pct_off_avg":0.5015200536124019,"tov_pct_off_avg":0.16833677147173728,"orb_pct_off_avg":0.2521255270615885},{"team_key":"SDC","opp_team_key":"SCL","team_name":"Sangalhos","opponent_name":"Sport Club Lusitânia","games":4,"wins":0,"losses":4,"win_pct":0.0,"net_rating_avg":-22.466833019194713,"off_rating_avg":96.73361445625133,"def_rating_avg":119.20044747544604,"pace_avg":79.43833333333333,"efg_pct_off_avg":0.4950341241843628,"tov_pct_off_avg":0.19170643768914675,"orb_pct_off_avg":0.22843803955545305},{"team_key":"SDC","opp_team_key":"SLB","team_name":"Sangalhos","opponent_name":"SL Benfica","games":1,"wins":1,"losses":0,"win_pct":1.0,"net_rating_avg":7.48752671284862,"off_rating_avg":106.32780082987551,"def_rating_avg":98.8402741170269,"pace_avg":76.5,"efg_pct_off_avg":0.6403508771929824,"tov_pct_off_avg":0.27230290456431533,"orb_pct_off_avg":0.3235294117647059},{"team_key":"SLB","opp_team_key":"AAC","team_name":"SL Benfica","opponent_name":"Académica Efapel","games":1,"wins":1,"losses":0,"win_pct":1.0,"net_rating_avg":6.771955765993937,"off_rating_avg":82.78145695364239,"def_rating_avg":76.00950118764845,"pace_avg":84.38,"efg_pct_off_avg":0.4014084507042254,"tov_pct_off_avg":0.21286660359508042,"orb_pct_off_avg":0.3},{"team_key":"SLB","opp_team_key":"ADG","team_name":"SL Benfica","opponent_name":"AD Galomar","games":4,"wins":1,"losses":3,"win_pct":0.25,"net_rating_avg":-0.5059713442895131,"off_rating_avg":95.97627696921911,"def_rating_avg":96.48224831350862,"pace_avg":78.66499999999999,"efg_pct_off_avg":0.4375699047224524,"tov_pct_off_avg":0.18165187066664373,"orb_pct_off_avg":0.3541269841269841},{"team_key":"SLB","opp_team_key":"BSA","team_name":"SL Benfica","opponent_name":"BSA - GALP","games":4,"wins":2,"losses":2,"win_pct":0.5,"net_rating_avg":-0.187475034935499,"off_rating_avg":86.19975967011501,"def_rating_avg":86.38723470505052,"pace_avg":78.32,"efg_pct_off_avg":0.4299911081197526,"tov_pct_off_avg":0.1980205857480653,"orb_pct_off_avg":0.24074440052700924},{"team_key":"SLB","opp_team_key":"CAB","team_name":"SL Benfica","opponent_name":"CAB Madeira","games":2,"wins":0,"losses":2,"win_pct":0.0,"net_rating_avg":-14.243218108024799,"off_rating_avg":82.55342926850585,"def_rating_avg":96.79664737653066,"pace_avg":77.24000000000001,"efg_pct_off_avg":0.40232974910394265,"tov_pct_off_avg":0.23056710541322079,"orb_pct_off_avg":0.2728937728937729},{"team_key":"SLB","opp_team_key":"CBQ","team_name":"SL Benfica","opponent_name":"Clube Basket de Queluz","games":3,"wins":1,"losses":2,"win_pct":0.3333333333333333,"net_rating_avg":7.835816386757244,"off_rating_avg":94.66607906618958,"def_rating_avg":86.83026267943234,"pace_avg":76.96,"efg_pct_off_avg":0.4538185828508409,"tov_pct_off_avg":0.20133531586351103,"orb_pct_off_avg":0.3218518518518519},{"team_key":"SLB","opp_team_key":"GCO","team_name":"SL Benfica","opponent_name":"Ginásio ANTRIX","games":2,"wins":1,"losses":1,"win_pct":0.5,"net_rating_avg":0.4610796973900051,"off_rating_avg":88.12925658783298,"def_rating_avg":87.66817689044298,"pace_avg":84.0,"efg_pct_off_avg":0.45236895161290325,"tov_pct_off_avg":0.2513175665967413,"orb_pct_off_avg":0.2894889663182346},{"team_key":"SLB","opp_team_key":"IBC","team_name":"SL Benfica","opponent_name":"Imortal LUZiGÁS","games":2,"wins":0,"losses":2,"win_pct":0.0,"net_rating_avg":-20.47419333954808,"off_rating_avg":80.89939786849294,"def_rating_avg":101.373591208041,"pace_avg":78.4,"efg_pct_off_avg":0.4291666666666667,"tov_pct_off_avg":0.27802091749708235,"orb_pct_off_avg":0.32291666666666663},{"team_key":"SLB","opp_team_key":"PSC","team_name":"SL Benfica","opponent_name":"Portimonense SC","games":2,"wins":1,"losses":1,"win_pct":0.5,"net_rating_avg":-6.343055542997526,"off_rating_avg":90.07073746497521,"def_rating_avg":96.41379300797274,"pace_avg":76.34,"efg_pct_off_avg":0.4100414078674949,"tov_pct_off_avg":0.17638393021332938,"orb_pct_off_avg":0.29244897959183674},{"team_key":"SLB","opp_team_key":"SBC","team_name":"SL Benfica","opponent_name":"Sampaense Inspecentro","games":2,"wins":1,"losses":1,"win_pct":0.5,"net_rating_avg":3.2729600176651132,"off_rating_avg":100.43830482439708,"def_rating_avg":97.16534480673198,"pace_avg":68.87,"efg_pct_off_avg":0.4475181598062954,"tov_pct_off_avg":0.14406390158529667,"orb_pct_off_avg":0.32897727272727273},{"team_key":"SLB","opp_team_key":"SCL","team_name":"SL Benfica","opponent_name":"Sport Club Lusitânia","games":2,"wins":0,"losses":2,"win_pct":0.0,"net_rating_avg":-12.726348788304172,"off_rating_avg":102.72501462722862,"def_rating_avg":115.4513634155328,"pace_avg":76.78,"efg_pct_off_avg":0.4737179487179487,"tov_pct_off_avg":0.1641824847365685,"orb_pct_off_avg":0.3153846153846154},{"team_key":"SLB","opp_team_key":"SDC","team_name":"SL Benfica","opponent_name":"Sangalhos","games":1,"wins":0,"losses":1,"win_pct":0.0,"net_rating_avg":-7.48752671284862,"off_rating_avg":98.8402741170269,"def_rating_avg":106.32780082987551,"pace_avg":76.5,"efg_pct_off_avg":0.39473684210526316,"tov_pct_off_avg":0.14496573537163943,"orb_pct_off_avg":0.45098039215686275}],"summary_by_phase":[],"phases":[]}